metadex/MG-RAST_API_downloader.py
metadex/Study.py
metadex/__init__.py
metadex/analysis.py
metadex/async_downloads.py
metadex/boruta_py.py
metadex/comparison.py
metadex/download_files.py
metadex/infotheo.py
metadex/lineage_dict.csv
metadex/metadex.py
metadex/mg-compare-functions.py
metadex/mg-get-annotation-set.py
metadex/mglib.py
metadex/preprocessing.py
metadex-0.9.50.dist-info/DESCRIPTION.rst
metadex-0.9.50.dist-info/METADATA
metadex-0.9.50.dist-info/RECORD
metadex-0.9.50.dist-info/WHEEL
metadex-0.9.50.dist-info/metadata.json
metadex-0.9.50.dist-info/top_level.txt
