Metadata-Version: 2.0
Name: metadex
Version: 0.9.50
Summary: UNKNOWN
Home-page: UNKNOWN
Author: Vibhu Chandrashekhar
Author-email: vibhu@outlook.com
License: MIT
Platform: UNKNOWN
Classifier: Development Status :: 4 - Beta
Classifier: Topic :: Scientific/Engineering :: Bio-Informatics
Classifier: License :: OSI Approved :: MIT License
Classifier: Programming Language :: Python :: 3.5
Requires-Dist: pandas
Requires-Dist: numpy
Requires-Dist: aiofiles
Requires-Dist: aiohttp
Requires-Dist: asyncio
Requires-Dist: Boruta
Requires-Dist: scikit-bio
Requires-Dist: scikit-learn
Requires-Dist: seaborn
Requires-Dist: matplotlib
Requires-Dist: brunel
Requires-Dist: biopython
